yandex_captcha_solver/__init__.py
yandex_captcha_solver/solver.py
yandex_captcha_solver-1.0.0.dist-info/licenses/LICENSE
yandex_captcha_solver-1.0.0.dist-info/METADATA
yandex_captcha_solver-1.0.0.dist-info/WHEEL
yandex_captcha_solver-1.0.0.dist-info/top_level.txt
yandex_captcha_solver-1.0.0.dist-info/RECORD
